aichatcoder/__init__.py
aichatcoder/cli.py
aichatcoder/global_config.py
aichatcoder/updater.py
aichatcoder-0.0.3.dist-info/METADATA
aichatcoder-0.0.3.dist-info/WHEEL
aichatcoder-0.0.3.dist-info/entry_points.txt
aichatcoder-0.0.3.dist-info/licenses/LICENSE
aichatcoder-0.0.3.dist-info/RECORD
