Metadata-Version: 2.4
Name: aichatcoder
Version: 0.0.3
Summary: Agent for generating and applying AI-powered coding prompts in your repository via a web UI
Project-URL: Homepage, https://aichatcoder.com
Project-URL: Repository, https://github.com/aichatcoder/aichatcoder
Project-URL: Issues, https://github.com/aichatcoder/aichatcoder/issues
Author-email: AiChatCoder Team <aichatcoder@gmail.com>
License-File: LICENSE
Classifier: License :: Other/Proprietary License
Classifier: Operating System :: OS Independent
Classifier: Programming Language :: Python :: 3
Requires-Python: >=3.8
Requires-Dist: click>=8.0
Requires-Dist: packaging>=23.0
Requires-Dist: pyyaml>=6.0
Requires-Dist: requests>=2.28.0
